setproj/__init__.py
setproj/__main__.py
setproj/__version__.py
setproj/langSetup.py
setproj-2.3.0.dist-info/LICENSE
setproj-2.3.0.dist-info/METADATA
setproj-2.3.0.dist-info/WHEEL
setproj-2.3.0.dist-info/entry_points.txt
setproj-2.3.0.dist-info/top_level.txt
setproj-2.3.0.dist-info/RECORD
