Metadata-Version: 2.1
Name: setproj
Version: 2.3.0
Summary: create projects in cli
Home-page: https://github.com/coolabhays/project-setup
Author: Abhay Shanker Pathak
Author-email: abhaysp9955@gmail.com
License: MIT
Keywords: project programming language
Platform: UNKNOWN
Classifier: Programming Language :: Python :: 3
Classifier: License :: OSI Approved :: MIT License
Classifier: Topic :: Utilities
Classifier: Topic :: Terminals
Classifier: Operating System :: POSIX
License-File: LICENSE
Requires-Dist: Click
